sbux/__init__.py
sbux/main.py
sbux/models/__init__.py
sbux/models/base.py
sbux/models/item.py
sbux/models/store.py
sbux-1.0.3.dist-info/LICENSE
sbux-1.0.3.dist-info/METADATA
sbux-1.0.3.dist-info/WHEEL
sbux-1.0.3.dist-info/RECORD
