Metadata-Version: 2.1
Name: sbux
Version: 1.0.3
Summary: An unofficial Starbucks Singapore (SG) software development kit (SDK).
Home-page: https://github.com/ngshiheng/sbux
License: MIT
Author: Jerry Ng
Author-email: ngshiheng@gmail.com
Requires-Python: >=3.9,<4.0
Classifier: License :: OSI Approved :: MIT License
Classifier: Programming Language :: Python :: 3
Classifier: Programming Language :: Python :: 3.9
Classifier: Programming Language :: Python :: 3.10
Classifier: Programming Language :: Python :: 3.11
Requires-Dist: dataclasses-json (==0.6.4)
Requires-Dist: requests (==2.31.0)
Requires-Dist: requests-cache (==1.1.1)
Project-URL: Repository, https://github.com/ngshiheng/sbux
